Metadata-Version: 2.1
Name: clustaar.authorize
Version: 1.0.0
Summary: Add a short description here!
Home-page: https://pyscaffold.org/
Author: qtaiclet
Author-email: quentin@clustaar.com
License: mit
Platform: any
Classifier: Development Status :: 4 - Beta
Classifier: Programming Language :: Python
Provides-Extra: testing
License-File: LICENSE.txt
License-File: AUTHORS.rst
